spylogger/__init__.py
spylogger/formatters.py
spylogger/pretty.py
spylogger/settings.py
spylogger-1.2.2.dist-info/DESCRIPTION.rst
spylogger-1.2.2.dist-info/METADATA
spylogger-1.2.2.dist-info/RECORD
spylogger-1.2.2.dist-info/WHEEL
spylogger-1.2.2.dist-info/metadata.json
spylogger-1.2.2.dist-info/top_level.txt
