Metadata-Version: 2.0
Name: spylogger
Version: 1.2.2
Summary: Python logging library
Home-page: https://github.com/devstuff-io/spylogger
Author: meganlkm
Author-email: devstuff.io@gmail.com
License: UNKNOWN
Keywords: logging,logs,pretty
Platform: UNKNOWN
Classifier: Intended Audience :: Developers
Classifier: License :: OSI Approved :: MIT License
Classifier: Operating System :: OS Independent
Classifier: Programming Language :: Python
Classifier: Topic :: System :: Logging
Provides-Extra: pretty
Provides-Extra: pretty
Requires-Dist: Pygments; extra == 'pretty'
Requires-Dist: pygments-json; extra == 'pretty'
Requires-Dist: pygments-solarized; extra == 'pretty'
